ProvenaInterfaces/APIResponses.py
ProvenaInterfaces/AsyncJobAPI.py
ProvenaInterfaces/AsyncJobModels.py
ProvenaInterfaces/AuthAPI.py
ProvenaInterfaces/DataStoreAPI.py
ProvenaInterfaces/HandleAPI.py
ProvenaInterfaces/HandleModels.py
ProvenaInterfaces/ProvenanceAPI.py
ProvenaInterfaces/ProvenanceModels.py
ProvenaInterfaces/RegistryAPI.py
ProvenaInterfaces/RegistryModels.py
ProvenaInterfaces/SearchAPI.py
ProvenaInterfaces/SentryMonitoring.py
ProvenaInterfaces/SharedTypes.py
ProvenaInterfaces/TestConfig.py
ProvenaInterfaces/__init__.py
ProvenaInterfaces/py.typed
ProvenaInterfaces/helpers/__init__.py
ProvenaInterfaces/helpers/helpers.py
ProvenaInterfaces/helpers/types.py
provena_interfaces-2.10.3.dist-info/METADATA
provena_interfaces-2.10.3.dist-info/WHEEL
provena_interfaces-2.10.3.dist-info/top_level.txt
provena_interfaces-2.10.3.dist-info/RECORD
