Metadata-Version: 2.1
Name: provena-interfaces
Version: 2.10.3
Summary: Interfaces for Provena Application (see https://provena.io)
Home-page: https://provena.io
Maintainer-email: rrap-mds-is-support@csiro.au
Requires-Dist: fastapi==0.88.0
Requires-Dist: pydantic[email]==1.10.17
Requires-Dist: email-validator
Requires-Dist: isodate
